src/__init__.py
src/cl0.py
src/closed_loop_lumped.dll
src/closed_loop_lumped.f90
src/closed_loop_lumped.so
src/cust_fns.f90
src/data_types.f90
src/elastance.f90
src/funcs.f90
src/inputs.f90
src/kind_parameter.f90
src/Makefile
src/opt.py
src/thermoregulation.f90
haemflow_cl0-0.1.4.dist-info/LICENSE
haemflow_cl0-0.1.4.dist-info/METADATA
haemflow_cl0-0.1.4.dist-info/WHEEL
haemflow_cl0-0.1.4.dist-info/RECORD
