Metadata-Version: 2.1
Name: haemflow-cl0
Version: 0.1.4
Summary: A haemodynamics solver for a closed loop 0D network with thermoregulation
License: GPLv3-or-later
Author: Alex
Author-email: adrysdale@protonmail.com
Requires-Python: >=3.10.0,<4.0.0
Classifier: License :: Other/Proprietary License
Classifier: Programming Language :: Python :: 3
Classifier: Programming Language :: Python :: 3.10
Classifier: Programming Language :: Python :: 3.11
Classifier: Programming Language :: Python :: 3.12
Requires-Dist: h5py (>=3.10.0,<4.0.0)
Requires-Dist: matplotlib (>=3.8.3,<4.0.0)
Requires-Dist: nevergrad (>=1.0.1,<2.0.0)
Requires-Dist: numpy (>=1.26.4,<2.0.0)
Requires-Dist: tqdm (>=4.66.2,<5.0.0)
